README.md
setup.py
colorexlib/__init__.py
colorexlib/colorex.py
colorexlib/test_colorex.py
colorexlib.egg-info/PKG-INFO
colorexlib.egg-info/SOURCES.txt
colorexlib.egg-info/dependency_links.txt
colorexlib.egg-info/top_level.txt
colorexlib/common/__init__.py
colorexlib/common/datastructures.py
colorexlib/common/test_datastructures.py
colorexlib/common/test_themes.py
colorexlib/common/themes.py
colorexlib/readers/CSVReader.py
colorexlib/readers/FileInputReader.py
colorexlib/readers/InputReader.py
colorexlib/readers/__init__.py
colorexlib/readers/test_CSVReader.py
colorexlib/writers/FileOutputWriter.py
colorexlib/writers/HTMLWriter.py
colorexlib/writers/OutputWriter.py
colorexlib/writers/__init__.py
colorexlib/writers/test_FileOutputWriter.py
colorexlib/writers/test_HTMLWriter.py