Metadata-Version: 2.1
Name: colorexlib
Version: 0.0.2
Summary: Fun data visualization that creatively uses color
Home-page: https://github.com/louisronron/ColorEx
Author: Louis Ronald
Author-email: louisronsonronald@gmail.com
License: UNKNOWN
Platform: UNKNOWN
Classifier: Programming Language :: Python :: 3
Classifier: License :: OSI Approved :: MIT License
Classifier: Operating System :: OS Independent
Requires-Python: >=3.7
